LICENSE
README.md
setup.py
pyEasyML/Settings.py
pyEasyML/__init__.py
pyEasyML/add_module.py
pyEasyML/cli.py
pyEasyML.egg-info/PKG-INFO
pyEasyML.egg-info/SOURCES.txt
pyEasyML.egg-info/dependency_links.txt
pyEasyML.egg-info/entry_points.txt
pyEasyML.egg-info/requires.txt
pyEasyML.egg-info/top_level.txt
pyEasyML/Classification/Classifier.py
pyEasyML/Classification/Factory.py
pyEasyML/Classification/SearchModelsBestParams.py
pyEasyML/Classification/__init__.py
pyEasyML/Classification/Models/AbstractClassificationModel.py
pyEasyML/Classification/Models/GradientBoostingClassifier.py
pyEasyML/Classification/Models/IsolationForest.py
pyEasyML/Classification/Models/KMeans.py
pyEasyML/Classification/Models/KNeighborsClassifier.py
pyEasyML/Classification/Models/LogisticRegression.py
pyEasyML/Classification/Models/RandomForestClassifier.py
pyEasyML/Classification/Models/SVC.py
pyEasyML/Classification/Models/XGBClassifier.py
pyEasyML/Classification/Models/__init__.py
pyEasyML/Configs/Config.py
pyEasyML/Configs/__init__.py
pyEasyML/Customize/Extension.py
pyEasyML/Customize/__init__.py
pyEasyML/Data/DataPreprocessing.py
pyEasyML/Data/FeatureSelection.py
pyEasyML/Data/__init__.py
pyEasyML/Email/Email.py
pyEasyML/Email/__init__.py
pyEasyML/NeuralNetworks/AbstractANN.py
pyEasyML/NeuralNetworks/__init__.py
pyEasyML/NeuralNetworks/AnomalyDetection/AnomalyDetector.py
pyEasyML/NeuralNetworks/AnomalyDetection/Factory.py
pyEasyML/NeuralNetworks/AnomalyDetection/__init__.py
pyEasyML/NeuralNetworks/Autoencoders/ConvolutionalAutoencoder.py
pyEasyML/NeuralNetworks/Autoencoders/DeepAutoencoder.py
pyEasyML/NeuralNetworks/Autoencoders/__init__.py
pyEasyML/NeuralNetworks/Layers/ConvolutionalLayers.py
pyEasyML/NeuralNetworks/Layers/DeepAutoencoderLayers.py
pyEasyML/NeuralNetworks/Layers/Layers.py
pyEasyML/NeuralNetworks/Layers/__init__.py
pyEasyML/OutlierDetection/__init__.py
pyEasyML/Regression/Factory.py
pyEasyML/Regression/Regressor.py
pyEasyML/Regression/__init__.py
pyEasyML/Regression/Models/AbstractRegressionModel.py
pyEasyML/Regression/Models/LinearSVR.py
pyEasyML/Regression/Models/Ridge.py
pyEasyML/Regression/Models/XGBRegressor.py
pyEasyML/Regression/Models/__init__.py
