Metadata-Version: 2.1
Name: pyEasyML
Version: 2.0.8
Summary: A python machine learning framework.
Home-page: UNKNOWN
Author: Rodrigo Santos de Carvalho
Author-email: <rodrigosc2401@gmail.com>
License: UNKNOWN
Keywords: python,AI,Machine Learning,Neural Networks
Platform: UNKNOWN
Classifier: Development Status :: 1 - Planning
Classifier: Intended Audience :: Developers
Classifier: Programming Language :: Python :: 3
Classifier: Operating System :: Unix
Classifier: Operating System :: MacOS :: MacOS X
Classifier: Operating System :: Microsoft :: Windows
License-File: LICENSE
